zivverscim/__init__.py
zivverscim/exceptions.py
zivverscim/external_connection.py
zivverscim/scim_connection_crud.py
zivverscim/wrapper.py
zivverscim-1.0.9.dist-info/LICENSE
zivverscim-1.0.9.dist-info/METADATA
zivverscim-1.0.9.dist-info/WHEEL
zivverscim-1.0.9.dist-info/top_level.txt
zivverscim-1.0.9.dist-info/RECORD
