Metadata-Version: 2.1
Name: zivverscim
Version: 1.0.9
Summary: A ZivverSCIM SDK for account manipulation
Home-page: https://github.com/Adapta-Innovation/zivverscim
Author: Igor van Spengen
Author-email: igor@adapta.nl
License: UNKNOWN
Project-URL: Bug Tracker, https://github.com/Adapta-Innovation/zivverscim/issues
Platform: UNKNOWN
Classifier: Programming Language :: Python :: 3
Classifier: License :: OSI Approved :: GNU General Public License v3 (GPLv3)
Classifier: Operating System :: OS Independent
Requires-Python: >=3.6
License-File: LICENSE
